actinia_module_plugin/__init__.py
actinia_module_plugin/endpoints.py
actinia_module_plugin/main.py
actinia_module_plugin/wsgi.py
actinia_module_plugin/api/__init__.py
actinia_module_plugin/api/actinia_templates.py
actinia_module_plugin/api/processing.py
actinia_module_plugin/api/modules/__init__.py
actinia_module_plugin/api/modules/actinia.py
actinia_module_plugin/api/modules/actinia_process.py
actinia_module_plugin/api/modules/combined.py
actinia_module_plugin/api/modules/grass.py
actinia_module_plugin/apidocs/__init__.py
actinia_module_plugin/apidocs/modules.py
actinia_module_plugin/apidocs/templates.py
actinia_module_plugin/apidocs/examples/__init__.py
actinia_module_plugin/apidocs/examples/gm_describemodule_get_example_v_random.json
actinia_module_plugin/apidocs/examples/pc_template.json
actinia_module_plugin/core/__init__.py
actinia_module_plugin/core/common.py
actinia_module_plugin/core/filter.py
actinia_module_plugin/core/processing.py
actinia_module_plugin/core/template_parameters.py
actinia_module_plugin/core/modules/__init__.py
actinia_module_plugin/core/modules/accessible_modules_kvdb_interface.py
actinia_module_plugin/core/modules/actinia_common.py
actinia_module_plugin/core/modules/actinia_global_templates.py
actinia_module_plugin/core/modules/actinia_user_templates.py
actinia_module_plugin/core/modules/grass.py
actinia_module_plugin/core/modules/grass_modules_kvdb_interface.py
actinia_module_plugin/core/modules/parser.py
actinia_module_plugin/core/modules/processor.py
actinia_module_plugin/core/templates/__init__.py
actinia_module_plugin/core/templates/global_templates.py
actinia_module_plugin/core/templates/user_templates.py
actinia_module_plugin/core/templates/user_templates_kvdb_interface.py
actinia_module_plugin/model/__init__.py
actinia_module_plugin/model/modules.py
actinia_module_plugin/model/responseModels.py
actinia_module_plugin/resources/__init__.py
actinia_module_plugin/resources/cli.py
actinia_module_plugin/resources/config.py
actinia_module_plugin-2.10.0.dist-info/licenses/LICENSE.txt
actinia_module_plugin-2.10.0.dist-info/METADATA
actinia_module_plugin-2.10.0.dist-info/WHEEL
actinia_module_plugin-2.10.0.dist-info/entry_points.txt
actinia_module_plugin-2.10.0.dist-info/top_level.txt
actinia_module_plugin-2.10.0.dist-info/RECORD
