Metadata-Version: 2.4
Name: actinia-module-plugin
Version: 2.10.0
Summary: A (RESTFUL) Flask application which adds module self-description and process-chain-template management to actinia-core
Author: Carmen Tawalika, Markus Neteler, Julia Haas, Guido Riembauer, Anika Weinmann, Jan Suleiman, Lina Krisztian
Project-URL: Homepage, https://github.com/mundialis/actinia-module-plugin
Project-URL: Tutorial, https://mundialis.github.io/actinia_core
Project-URL: API_Docs, https://redocly.github.io/redoc/?url=https://actinia.mundialis.de/latest/swagger.json
Keywords: processing,earth observation,cloud-based processing,rest api,gis,grass gis,osgeo
Classifier: License :: OSI Approved :: Apache Software License
Classifier: Programming Language :: Python :: 3
Requires-Python: >=3.8
License-File: LICENSE.txt
Requires-Dist: actinia-rest-lib>=1.0.0
Requires-Dist: actinia-processing-lib>=1.1.1
Requires-Dist: colorlog>=4.2.1
Requires-Dist: xmltodict
Provides-Extra: test
Requires-Dist: pytest; extra == "test"
Requires-Dist: pytest-cov; extra == "test"
Dynamic: license-file
